pdf2df/__init__.py
pdf2df/extraction.py
pdf2df-0.0.3.dist-info/LICENSE
pdf2df-0.0.3.dist-info/METADATA
pdf2df-0.0.3.dist-info/WHEEL
pdf2df-0.0.3.dist-info/top_level.txt
pdf2df-0.0.3.dist-info/RECORD
