Metadata-Version: 2.1
Name: pdf2df
Version: 0.0.3
Summary: Extract data from pdf to a dataframe
Home-page: UNKNOWN
Author: Rohit Thakur
Author-email: fordatascience12@gmail.com
License: UNKNOWN
Keywords: python,pymupdf,extract pdf,extract text,dataframe
Platform: UNKNOWN
Classifier: Development Status :: 1 - Planning
Classifier: Intended Audience :: Developers
Classifier: Programming Language :: Python :: 3
Classifier: Operating System :: Unix
Classifier: Operating System :: MacOS :: MacOS X
Classifier: Operating System :: Microsoft :: Windows
Requires-Dist: fitz
Requires-Dist: pymupdf
Requires-Dist: pandas
